mqtt5-0.2.0.dist-info/METADATA
mqtt5-0.2.0.dist-info/WHEEL
mqtt5-0.2.0.dist-info/licenses/LICENSE
mqtt5/__init__.py
mqtt5/__init__.pyi
mqtt5/mqtt5.abi3.so
mqtt5/py.typed
mqtt5-0.2.0.dist-info/RECORD
