Metadata-Version: 2.4
Name: mqtt5
Version: 0.2.0
Classifier: Programming Language :: Python :: 3.10
Classifier: Programming Language :: Python :: 3.11
Classifier: Programming Language :: Python :: 3.12
Classifier: Programming Language :: Python :: 3.13
Classifier: Programming Language :: Python :: 3.14
Classifier: Programming Language :: Rust
Classifier: Typing :: Typed
Classifier: Intended Audience :: Developers
Classifier: License :: OSI Approved :: BSD License
Classifier: Operating System :: OS Independent
License-File: LICENSE
Summary: The MQTTv5 protocol for Python written in Rust
Author-email: Felix Böhm <f@bo3hm.com>
Requires-Python: >=3.10, <4.0
Project-URL: Source, https://github.com/empicano/mqtt5
Project-URL: Issue tracker, https://github.com/empicano/mqtt5/issues
